odoo/addons/delivery_roulier_laposte_fr/README.rst
odoo/addons/delivery_roulier_laposte_fr/__init__.py
odoo/addons/delivery_roulier_laposte_fr/__manifest__.py
odoo/addons/delivery_roulier_laposte_fr/data/delivery.xml
odoo/addons/delivery_roulier_laposte_fr/i18n/delivery_roulier_laposte_fr.pot
odoo/addons/delivery_roulier_laposte_fr/i18n/es.po
odoo/addons/delivery_roulier_laposte_fr/i18n/it.po
odoo/addons/delivery_roulier_laposte_fr/models/__init__.py
odoo/addons/delivery_roulier_laposte_fr/models/delivery.py
odoo/addons/delivery_roulier_laposte_fr/models/stock_picking.py
odoo/addons/delivery_roulier_laposte_fr/models/stock_quant_package.py
odoo/addons/delivery_roulier_laposte_fr/readme/CONFIGURE.rst
odoo/addons/delivery_roulier_laposte_fr/readme/CONTRIBUTORS.rst
odoo/addons/delivery_roulier_laposte_fr/readme/CREDITS.rst
odoo/addons/delivery_roulier_laposte_fr/readme/DESCRIPTION.rst
odoo/addons/delivery_roulier_laposte_fr/static/description/icon.png
odoo/addons/delivery_roulier_laposte_fr/static/description/index.html
odoo/addons/delivery_roulier_laposte_fr/static/description/laposte_small.png
odoo/addons/delivery_roulier_laposte_fr/static/description/logo.jpg
odoo/addons/delivery_roulier_laposte_fr/tests/__init__.py
odoo/addons/delivery_roulier_laposte_fr/tests/test_laposte_label_dom.py
odoo/addons/delivery_roulier_laposte_fr/tests/test_laposte_label_france.py
odoo/addons/delivery_roulier_laposte_fr/tests/cassettes/LaposteLabelDomCase.test_labels.yaml
odoo/addons/delivery_roulier_laposte_fr/tests/cassettes/LaposteLabelFranceCase.test_labels.yaml
odoo/addons/delivery_roulier_laposte_fr/views/stock_picking.xml
odoo_addon_delivery_roulier_laposte_fr-16.0.1.0.0.6.dist-info/METADATA
odoo_addon_delivery_roulier_laposte_fr-16.0.1.0.0.6.dist-info/WHEEL
odoo_addon_delivery_roulier_laposte_fr-16.0.1.0.0.6.dist-info/top_level.txt
odoo_addon_delivery_roulier_laposte_fr-16.0.1.0.0.6.dist-info/RECORD
